pytest_sqlfluff.py
pytest_sqlfluff-0.1.1.dist-info/LICENSE
pytest_sqlfluff-0.1.1.dist-info/WHEEL
pytest_sqlfluff-0.1.1.dist-info/entry_points.txt
pytest_sqlfluff-0.1.1.dist-info/METADATA
pytest_sqlfluff-0.1.1.dist-info/RECORD
